scripts/gen_changelog.py
scripts/gen_ref_pages.py
sleap/__init__.py
sleap/cli.py
sleap/diagnostic.py
sleap/legacy_cli_adaptors.py
sleap/message.py
sleap/prefs.py
sleap/rangelist.py
sleap/util.py
sleap/version.py
sleap/config/colors.yaml
sleap/config/frame_range_form.yaml
sleap/config/head_type_form.yaml
sleap/config/labeled_clip_form.yaml
sleap/config/path_prefixes.yaml
sleap/config/pipeline_form.yaml
sleap/config/shortcuts.yaml
sleap/config/suggestions.yaml
sleap/config/training_editor_form.yaml
sleap/config/video_clip_form.yaml
sleap/gui/__init__.py
sleap/gui/app.py
sleap/gui/background.png
sleap/gui/color.py
sleap/gui/commands.py
sleap/gui/config_utils.py
sleap/gui/dataviews.py
sleap/gui/icon.png
sleap/gui/shortcuts.py
sleap/gui/state.py
sleap/gui/suggestions.py
sleap/gui/utils.py
sleap/gui/web.py
sleap/gui/dialogs/__init__.py
sleap/gui/dialogs/delete.py
sleap/gui/dialogs/export_clip.py
sleap/gui/dialogs/filedialog.py
sleap/gui/dialogs/formbuilder.py
sleap/gui/dialogs/frame_range.py
sleap/gui/dialogs/importvideos.py
sleap/gui/dialogs/merge.py
sleap/gui/dialogs/message.py
sleap/gui/dialogs/metrics.py
sleap/gui/dialogs/missingfiles.py
sleap/gui/dialogs/query.py
sleap/gui/dialogs/shortcuts.py
sleap/gui/learning/__init__.py
sleap/gui/learning/configs.py
sleap/gui/learning/dialog.py
sleap/gui/learning/receptivefield.py
sleap/gui/learning/runners.py
sleap/gui/overlays/__init__.py
sleap/gui/overlays/base.py
sleap/gui/overlays/confmaps.py
sleap/gui/overlays/instance.py
sleap/gui/overlays/pafs.py
sleap/gui/overlays/tracks.py
sleap/gui/widgets/__init__.py
sleap/gui/widgets/docks.py
sleap/gui/widgets/imagedir.py
sleap/gui/widgets/monitor.py
sleap/gui/widgets/mpl.py
sleap/gui/widgets/multicheck.py
sleap/gui/widgets/slider.py
sleap/gui/widgets/video.py
sleap/gui/widgets/video_worker.py
sleap/gui/widgets/views.py
sleap/info/__init__.py
sleap/info/align.py
sleap/info/feature_suggestions.py
sleap/info/labels.py
sleap/info/metrics.py
sleap/info/summary.py
sleap-1.5.1.dist-info/licenses/LICENSE
sleap-1.5.1.dist-info/METADATA
sleap-1.5.1.dist-info/WHEEL
sleap-1.5.1.dist-info/entry_points.txt
sleap-1.5.1.dist-info/top_level.txt
sleap-1.5.1.dist-info/RECORD
