Metadata-Version: 2.4
Name: sleap
Version: 1.5.1
Summary: SLEAP (Social LEAP Estimates Animal Poses) is a deep learning framework for animal pose tracking.
Author-email: Liezl Maree <lmaree@salk.edu>, Talmo Pereira <talmo@salk.edu>
License: BSD-3-Clause
Project-URL: Homepage, https://sleap.ai
Project-URL: Documentation, https://sleap.ai/
Project-URL: Bug Tracker, https://github.com/talmolab/sleap/issues
Project-URL: Source Code, https://github.com/talmolab/sleap
Keywords: deep learning,pose estimation,tracking,neuroscience
Classifier: Intended Audience :: Science/Research
Classifier: License :: OSI Approved :: BSD License
Classifier: Natural Language :: English
Classifier: Operating System :: OS Independent
Classifier: Programming Language :: Python :: 3.11
Classifier: Programming Language :: Python :: 3.12
Classifier: Programming Language :: Python :: 3.13
Classifier: Topic :: Scientific/Engineering
Classifier: Topic :: Scientific/Engineering :: Artificial Intelligence
Classifier: Topic :: Scientific/Engineering :: Image Processing
Requires-Python: >=3.11
License-File: LICENSE
Requires-Dist: attrs
Requires-Dist: cattrs
Requires-Dist: omegaconf
Requires-Dist: imageio
Requires-Dist: imageio-ffmpeg
Requires-Dist: imgstore
Requires-Dist: jsmin
Requires-Dist: jsonpickle
Requires-Dist: markupsafe
Requires-Dist: ndx-pose
Requires-Dist: networkx
Requires-Dist: nixio
Requires-Dist: numpy
Requires-Dist: opencv-python
Requires-Dist: pandas
Requires-Dist: psutil
Requires-Dist: pykalman
Requires-Dist: pynwb
Requires-Dist: PySide6
Requires-Dist: python-rapidjson
Requires-Dist: pyyaml
Requires-Dist: pyzmq
Requires-Dist: qtpy
Requires-Dist: rich
Requires-Dist: scikit-image
Requires-Dist: scikit-learn
Requires-Dist: scipy
Requires-Dist: seaborn
Requires-Dist: urllib3
Requires-Dist: albumentations
Requires-Dist: requests
Requires-Dist: matplotlib
Requires-Dist: sleap-io[all]>=0.5.3
Provides-Extra: dev
Requires-Dist: pytest; extra == "dev"
Requires-Dist: pytest-cov; extra == "dev"
Requires-Dist: pytest-qt>=4.4.0; extra == "dev"
Requires-Dist: pytest-xvfb; extra == "dev"
Requires-Dist: ruff; extra == "dev"
Provides-Extra: docs
Requires-Dist: mkdocs; extra == "docs"
Requires-Dist: mkdocs-material; extra == "docs"
Requires-Dist: mkdocs-jupyter; extra == "docs"
Requires-Dist: mkdocstrings[python]; extra == "docs"
Requires-Dist: mkdocs-gen-files; extra == "docs"
Requires-Dist: mkdocs-literate-nav; extra == "docs"
Requires-Dist: mkdocs-section-index; extra == "docs"
Requires-Dist: mike; extra == "docs"
Provides-Extra: jupyter
Requires-Dist: jupyter; extra == "jupyter"
Requires-Dist: jupyterlab; extra == "jupyter"
Provides-Extra: nn
Requires-Dist: sleap-nn[torch]>=0.0.2; extra == "nn"
Provides-Extra: nn-cpu
Requires-Dist: sleap-nn[torch]>=0.0.2; extra == "nn-cpu"
Provides-Extra: nn-cuda128
Requires-Dist: sleap-nn[torch]>=0.0.2; extra == "nn-cuda128"
Provides-Extra: nn-cuda118
Requires-Dist: sleap-nn[torch]>=0.0.2; extra == "nn-cuda118"
Dynamic: license-file
